{
  "key": "zugferd-datenformat-2.2.0",
  "language": "de",
  "short_name": "ZUGFeRD Data Format v2.2.0 14.02.2022",
  "name": "ZUGFeRD Datenformat Version 2.2.0 14.02.2022",
  "category": "Proprietary Free",
  "owner": "ZUGFeRD Community",
  "homepage_url": "https://github.com/ZUGFeRD/corpus/blob/master/XML-Rechnung/CII/EN16931_1_Teilrechnung.cii.xml",
  "spdx_license_key": "LicenseRef-scancode-zugferd-datenformat-2.2.0",
  "ignorable_urls": [
    "http://www.ferd-net.de/"
  ],
  "text": "<?xml version='1.0' encoding='UTF-8' ?>\n<!-- English disclaimer below.-->\n<!--Nutzungsrechte \nZUGFeRD Datenformat Version 2.2.0, 14.02.2022\nBeispiel Version 14.02.2022\n \nZweck des Forums elektronisch Rechnung Deutschland, welches am 31. M\u00e4rz 2010 unter der Arbeitsgemeinschaft f\u00fcr \nwirtschaftliche Verwaltung e. V. gegr\u00fcndet wurde, ist u. a. die Schaffung und Spezifizierung eines offenen Datenformats \nf\u00fcr strukturierten elektronischen Datenaustausch auf der Grundlage offener und nicht diskriminierender, standardisierter \nTechnologien (\u201eZUGFeRD Datenformat\u201c).\n \nDas ZUGFeRD Datenformat wird nach Ma\u00dfgabe des FeRD sowohl Unternehmen als auch der \u00f6ffentlichen Verwaltung \nfrei zug\u00e4nglich gemacht. Hierf\u00fcr bietet FeRD allen Unternehmen und Organisationen der \u00f6ffentlichen Verwaltung eine \nLizenz f\u00fcr die Nutzung des urheberrechtlich gesch\u00fctzten ZUGFeRD-Datenformats zu fairen, sachgerechten und nicht \ndiskriminierenden Bedingungen an.\n \nDie Spezifikation des FeRD zur Implementierung des ZUGFeRD Datenformats ist in ihrer jeweils geltenden Fassung \nabrufbar unter www.ferd-net.de.\n \nIm Einzelnen schlie\u00dft die Nutzungsgew\u00e4hrung ein: \n=====================================\n \nFeRD r\u00e4umt eine Lizenz f\u00fcr die Nutzung des urheberrechtlich gesch\u00fctzten ZUGFeRD Datenformats in der jeweils \ngeltenden und akzeptierten Fassung (www.ferd-net.de) ein. \nDie Lizenz beinhaltet ein unwiderrufliches Nutzungsrecht einschlie\u00dflich des Rechts der Weiterentwicklung, \nWeiterbearbeitung und Verbindung mit anderen Produkten.\nDie Lizenz gilt insbesondere f\u00fcr die Entwicklung, die Gestaltung, die Herstellung, den Verkauf, die Nutzung oder \nanderweitige Verwendung des ZUGFeRD Datenformats f\u00fcr Hardware- und/oder Softwareprodukte sowie sonstige \nAnwendungen und Dienste. \nDiese Lizenz schlie\u00dft nicht die wesentlichen Patente der Mitglieder von FeRD ein. Als wesentliche Patente sind Patente \nund Patentanmeldungen weltweit zu verstehen, die einen oder mehrere Patentanspr\u00fcche beinhalten, bei denen es sich um \nnotwendige Anspr\u00fcche handelt. Notwendige Anspr\u00fcche sind lediglich jene Anspr\u00fcche der Wesentlichen Patente, die durch \ndie Implementierung des ZUGFeRD Datenformats notwendigerweise verletzt w\u00fcrden. \nDer Lizenznehmer ist berechtigt, seinen jeweiligen Konzerngesellschaften ein unbefristetes, weltweites, nicht \u00fcbertragbares, \nunwiderrufliches Nutzungsrecht einschlie\u00dflich des Rechts der Weiterentwicklung, Weiterbearbeitung und Verbindung mit \nanderen Produkten einzur\u00e4umen. \n \nDie Lizenz wird kostenfrei zur Verf\u00fcgung gestellt. \n \nAu\u00dfer im Falle vors\u00e4tzlichen Verschuldens oder grober Fahrl\u00e4ssigkeit haftet FeRD weder f\u00fcr Nutzungsausfall, entgangenen \nGewinn, Datenverlust, Kommunikationsverlust, Einnahmeausfall, Vertragseinbu\u00dfen, Gesch\u00e4ftsausfall oder f\u00fcr Kosten, \nSch\u00e4den, Verluste oder Haftpflichten im Zusammenhang mit einer Unterbrechung der Gesch\u00e4ftst\u00e4tigkeit, noch f\u00fcr konkrete, \nbeil\u00e4ufig entstandene, mittelbare Sch\u00e4den, Straf- oder Folgesch\u00e4den und zwar auch dann nicht, wenn die M\u00f6glichkeit der \nKosten, Verluste bzw. Sch\u00e4den h\u00e4tte normalerweise vorhergesehen werden k\u00f6nnen.-->\n \n <!--Right of use \nZUGFeRD Data format version 2.2.0, February 14th, 2022\n \nThe purpose of the Forum elektronische Rechnung Deutschland (FeRD), which was founded on March 31, 2010 under the \numbrella of Arbeitsgemeinschaft f\u00fcr wirtschaftliche Verwaltung e. V., is, among other things, to create and specify an \nopen data format for structured electronic data exchange on the basis of open and non discriminatory, standardised \ntechnologies (\"ZUGFeRD data format\").\n \nThe ZUGFeRD data format is used by both companies and public administration according to the FeRD \nmade freely accessible. For this purpose FeRD offers all companies and organisations of the public administration a \nLicense to use the copyrighted ZUGFeRD data format in a fair, appropriate and non \ndiscriminatory conditions.\n \nThe specification of the FeRD for the implementation of the ZUGFeRD data format is, in its currently valid version \navailable at www.ferd-net.de.\n \nIn detail, the grant of use includes \n=====================================\n \nFeRD grants a license for the use of the copyrighted ZUGFeRD data format in the respective \nvalid and accepted version (www.ferd-net.de). \nThe license includes an irrevocable right of use including the right of further development, \nFurther processing and connection with other products.\nThe license applies in particular to the development, design, production, sale, use or \nother use of the ZUGFeRD data format for hardware and/or software products and other \napplications and services. \nThis license does not include the essential patents of the members of FeRD. The essential patents are patents \nand patent applications worldwide which contain one or more claims that are \nnecessary claims. Necessary claims are only those claims of the essential patents which are \nthe implementation of the ZUGFeRD data format would necessarily be violated. \nThe Licensee is entitled to provide its respective group companies with an unlimited, worldwide, non-transferable, \nirrevocable right of use including the right of further development, further processing and connection with \nother products. \n \nThe license is provided free of charge. \n \nExcept in the case of intentional fault or gross negligence, FeRD is not liable for loss of use, loss of \nProfit, loss of data, loss of communication, loss of revenue, loss of contracts, loss of business or for costs \ndamages, losses or liabilities in connection with an interruption of business, nor for concrete, \nincidental, indirect, punitive or consequential damages, even if the possibility of \ncosts, losses or damages could normally have been foreseen.-->\n\n<rsm:CrossIndustryInvoice xmlns:rsm=\"urn:un:unece:uncefact:data:standard:CrossIndustryInvoice:100\" xmlns:qdt=\"urn:un:unece:uncefact:data:standard:QualifiedDataType:100\" xmlns:ram=\"urn:un:unece:uncefact:data:standard:ReusableAggregateBusinessInformationEntity:100\" xmlns:xs=\"http://www.w3.org/2001/XMLSchema\" xmlns:udt=\"urn:un:unece:uncefact:data:standard:UnqualifiedDataType:100\">\n  <rsm:ExchangedDocumentContext>\n    <ram:GuidelineSpecifiedDocumentContextParameter>\n      <ram:ID>urn:cen.eu:en16931:2017</ram:ID>\n    </ram:GuidelineSpecifiedDocumentContextParameter>\n  </rsm:ExchangedDocumentContext>\n  <rsm:ExchangedDocument>\n    <ram:ID>471102</ram:ID>\n    <ram:TypeCode>380</ram:TypeCode>\n    <ram:IssueDateTime>\n      <udt:DateTimeString format=\"102\">20180605</udt:DateTimeString>\n    </ram:IssueDateTime>\n    <ram:IncludedNote>\n      <ram:Content>Rechnung gem\u00e4\u00df Bestellung Nr. 2018-471331 vom 01.03.2018.</ram:Content>\n    </ram:IncludedNote>\n    <ram:IncludedNote>\n      <ram:Content>Es bestehen Rabatt- und Bonusvereinbarungen.</ram:Content>\n      <ram:SubjectCode>AAK</ram:SubjectCode>\n    </ram:IncludedNote>\n    <ram:IncludedNote>\n      <ram:Content>Lieferant GmbH\t\t\t\t\nLieferantenstra\u00dfe 20\t\t\t\t\n80333 M\u00fcnchen\t\t\t\t\nDeutschland\t\t\t\t\nGesch\u00e4ftsf\u00fchrer: Hans Muster\nHandelsregisternummer: H A 123\n      </ram:Content>\n      <ram:SubjectCode>REG</ram:SubjectCode>\n    </ram:IncludedNote>\n  </rsm:ExchangedDocument>\n  <rsm:SupplyChainTradeTransaction>\n    <ram:IncludedSupplyChainTradeLineItem>\n      <ram:AssociatedDocumentLineDocument>\n        <ram:LineID>1</ram:LineID>\n\t\t  <ram:IncludedNote>\n          <ram:Content>Wir erlauben uns Ihnen folgende Positionen aus der Lieferung Nr. 2018-51112 in Rechnung zu stellen:</ram:Content>\n        </ram:IncludedNote>\n      </ram:AssociatedDocumentLineDocument>\n      <ram:SpecifiedTradeProduct>\n        <ram:GlobalID schemeID=\"0160\">4012345001235</ram:GlobalID>\n        <ram:SellerAssignedID>KR3M</ram:SellerAssignedID>\n        <ram:BuyerAssignedID/>\n        <ram:Name>Kunstrasen gr\u00fcn 3m breit</ram:Name>\n        <ram:Description>300cm x 100 cm</ram:Description>\n      </ram:SpecifiedTradeProduct>\n      <ram:SpecifiedLineTradeAgreement>\n        <ram:GrossPriceProductTradePrice>\n          <ram:ChargeAmount>4.0000</ram:ChargeAmount>\n          <ram:AppliedTradeAllowanceCharge>\n\t\t\t<ram:ChargeIndicator>\n              <udt:Indicator>false</udt:Indicator>\n\t\t\t</ram:ChargeIndicator>\n\t\t\t<ram:ActualAmount>0.6667</ram:ActualAmount>\n          </ram:AppliedTradeAllowanceCharge>\n        </ram:GrossPriceProductTradePrice>\n        <ram:NetPriceProductTradePrice>\n          <ram:ChargeAmount>3.3333</ram:ChargeAmount>\n        </ram:NetPriceProductTradePrice>\n      </ram:SpecifiedLineTradeAgreement>\n      <ram:SpecifiedLineTradeDelivery>\n        <ram:BilledQuantity unitCode=\"MTK\">3.0000</ram:BilledQuantity>\n      </ram:SpecifiedLineTradeDelivery>\n      <ram:SpecifiedLineTradeSettlement>\n        <ram:ApplicableTradeTax>\n          <ram:TypeCode>VAT</ram:TypeCode>\n          <ram:CategoryCode>S</ram:CategoryCode>\n          <ram:RateApplicablePercent>19.00</ram:RateApplicablePercent>\n        </ram:ApplicableTradeTax>\n        <ram:SpecifiedTradeSettlementLineMonetarySummation>\n          <ram:LineTotalAmount>10.00</ram:LineTotalAmount>\n        </ram:SpecifiedTradeSettlementLineMonetarySummation>\n      </ram:SpecifiedLineTradeSettlement>\n    </ram:IncludedSupplyChainTradeLineItem>\n    <ram:IncludedSupplyChainTradeLineItem>\n      <ram:AssociatedDocumentLineDocument>\n        <ram:LineID>2</ram:LineID>\n        <ram:IncludedNote>\n          <ram:Content>Bestellt wurden 5 kg Schweinesteak. Mit dieser Rechnung werden nur die bereits gelieferten Steaks berechnet. Die noch offenen 4 kg Schweinesteak werden separat geliefert und berechnet.</ram:Content>\n        </ram:IncludedNote>\n      </ram:AssociatedDocumentLineDocument>\n      <ram:SpecifiedTradeProduct>\n        <ram:GlobalID schemeID=\"0160\">4000050986428</ram:GlobalID>\n        <ram:SellerAssignedID>SFK5</ram:SellerAssignedID>\n        <ram:BuyerAssignedID/>\n        <ram:Name>Schweinesteak</ram:Name>\n        <ram:Description>Schweinesteak aus Deutschland</ram:Description>\n      </ram:SpecifiedTradeProduct>\n      <ram:SpecifiedLineTradeAgreement>\n        <ram:GrossPriceProductTradePrice>\n          <ram:ChargeAmount>5.5000</ram:ChargeAmount>\n        </ram:GrossPriceProductTradePrice>\n        <ram:NetPriceProductTradePrice>\n          <ram:ChargeAmount>5.5000</ram:ChargeAmount>\n        </ram:NetPriceProductTradePrice>\n      </ram:SpecifiedLineTradeAgreement>\n      <ram:SpecifiedLineTradeDelivery>\n        <ram:BilledQuantity unitCode=\"KGM\">1.0000</ram:BilledQuantity>\n      </ram:SpecifiedLineTradeDelivery>\n      <ram:SpecifiedLineTradeSettlement>\n        <ram:ApplicableTradeTax>\n          <ram:TypeCode>VAT</ram:TypeCode>\n          <ram:CategoryCode>S</ram:CategoryCode>\n          <ram:RateApplicablePercent>7.00</ram:RateApplicablePercent>\n        </ram:ApplicableTradeTax>\n        <ram:SpecifiedTradeSettlementLineMonetarySummation>\n          <ram:LineTotalAmount>5.50</ram:LineTotalAmount>\n        </ram:SpecifiedTradeSettlementLineMonetarySummation>\n      </ram:SpecifiedLineTradeSettlement>\n    </ram:IncludedSupplyChainTradeLineItem>\n    <ram:IncludedSupplyChainTradeLineItem>\n      <ram:AssociatedDocumentLineDocument>\n        <ram:LineID>3</ram:LineID>\n      </ram:AssociatedDocumentLineDocument>\n      <ram:SpecifiedTradeProduct>\n        <ram:GlobalID schemeID=\"0160\">4000001234561</ram:GlobalID>\n        <ram:SellerAssignedID>GTRWA5</ram:SellerAssignedID>\n        <ram:BuyerAssignedID/>\n        <ram:Name>Mineralwasser Medium \n12 x 1,0l PET\n        </ram:Name>\n      </ram:SpecifiedTradeProduct>\n      <ram:SpecifiedLineTradeAgreement>\n        <ram:GrossPriceProductTradePrice>\n          <ram:ChargeAmount>5.4900</ram:ChargeAmount>\n        </ram:GrossPriceProductTradePrice>\n        <ram:NetPriceProductTradePrice>\n          <ram:ChargeAmount>5.4900</ram:ChargeAmount>\n        </ram:NetPriceProductTradePrice>\n      </ram:SpecifiedLineTradeAgreement>\n      <ram:SpecifiedLineTradeDelivery>\n        <ram:BilledQuantity unitCode=\"H87\">20.0000</ram:BilledQuantity>\n      </ram:SpecifiedLineTradeDelivery>\n      <ram:SpecifiedLineTradeSettlement>\n        <ram:ApplicableTradeTax>\n          <ram:TypeCode>VAT</ram:TypeCode>\n          <ram:CategoryCode>S</ram:CategoryCode>\n          <ram:RateApplicablePercent>7.00</ram:RateApplicablePercent>\n        </ram:ApplicableTradeTax>\n        <ram:SpecifiedTradeSettlementLineMonetarySummation>\n          <ram:LineTotalAmount>109.80</ram:LineTotalAmount>\n        </ram:SpecifiedTradeSettlementLineMonetarySummation>\n      </ram:SpecifiedLineTradeSettlement>\n    </ram:IncludedSupplyChainTradeLineItem>\n    <ram:IncludedSupplyChainTradeLineItem>\n      <ram:AssociatedDocumentLineDocument>\n        <ram:LineID>4</ram:LineID>\n      </ram:AssociatedDocumentLineDocument>\n      <ram:SpecifiedTradeProduct>\n        <ram:GlobalID schemeID=\"0160\">4000001234578</ram:GlobalID>\n        <ram:SellerAssignedID>PFA5</ram:SellerAssignedID>\n        <ram:BuyerAssignedID/>\n        <ram:Name>Pfand</ram:Name>\n      </ram:SpecifiedTradeProduct>\n      <ram:SpecifiedLineTradeAgreement>\n        <ram:GrossPriceProductTradePrice>\n          <ram:ChargeAmount>2.7700</ram:ChargeAmount>\n        </ram:GrossPriceProductTradePrice>\n        <ram:NetPriceProductTradePrice>\n          <ram:ChargeAmount>2.7700</ram:ChargeAmount>\n        </ram:NetPriceProductTradePrice>\n      </ram:SpecifiedLineTradeAgreement>\n      <ram:SpecifiedLineTradeDelivery>\n        <ram:BilledQuantity unitCode=\"C62\">20.0000</ram:BilledQuantity>\n      </ram:SpecifiedLineTradeDelivery>\n      <ram:SpecifiedLineTradeSettlement>\n        <ram:ApplicableTradeTax>\n          <ram:TypeCode>VAT</ram:TypeCode>\n          <ram:CategoryCode>S</ram:CategoryCode>\n          <ram:RateApplicablePercent>19.00</ram:RateApplicablePercent>\n        </ram:ApplicableTradeTax>\n        <ram:SpecifiedTradeSettlementLineMonetarySummation>\n          <ram:LineTotalAmount>55.46</ram:LineTotalAmount>\n        </ram:SpecifiedTradeSettlementLineMonetarySummation>\n      </ram:SpecifiedLineTradeSettlement>\n    </ram:IncludedSupplyChainTradeLineItem>\n    <ram:ApplicableHeaderTradeAgreement>\n      <ram:SellerTradeParty>\n\t\t<ram:ID>549910</ram:ID>\n        <ram:GlobalID schemeID=\"0088\">4000001123452</ram:GlobalID>\n        <ram:Name>Lieferant GmbH</ram:Name>\n        <ram:PostalTradeAddress>\n          <ram:PostcodeCode>80333</ram:PostcodeCode>\n          <ram:LineOne>Lieferantenstra\u00dfe 20</ram:LineOne>\n          <ram:CityName>M\u00fcnchen</ram:CityName>\n          <ram:CountryID>DE</ram:CountryID>\n        </ram:PostalTradeAddress>\n        <ram:SpecifiedTaxRegistration>\n          <ram:ID schemeID=\"FC\">201/113/40209</ram:ID>\n        </ram:SpecifiedTaxRegistration>\n        <ram:SpecifiedTaxRegistration>\n          <ram:ID schemeID=\"VA\">DE123456789</ram:ID>\n        </ram:SpecifiedTaxRegistration>\n      </ram:SellerTradeParty>\n      <ram:BuyerTradeParty>\n        <ram:ID>GE2020211</ram:ID>\n        <ram:Name>Kunden AG Mitte</ram:Name>\n        <ram:PostalTradeAddress>\n          <ram:PostcodeCode>69876</ram:PostcodeCode>\n          <ram:LineOne>Kundenstra\u00dfe 15</ram:LineOne>\n          <ram:CityName>Frankfurt</ram:CityName>\n          <ram:CountryID>DE</ram:CountryID>\n        </ram:PostalTradeAddress>\n      </ram:BuyerTradeParty>\n      <ram:BuyerOrderReferencedDocument>\n        <ram:IssuerAssignedID>2018-471331</ram:IssuerAssignedID>\n      </ram:BuyerOrderReferencedDocument>\n    </ram:ApplicableHeaderTradeAgreement>\n    <ram:ApplicableHeaderTradeDelivery>\n      <ram:ActualDeliverySupplyChainEvent>\n        <ram:OccurrenceDateTime>\n          <udt:DateTimeString format=\"102\">20180603</udt:DateTimeString>\n        </ram:OccurrenceDateTime>\n      </ram:ActualDeliverySupplyChainEvent>\n    </ram:ApplicableHeaderTradeDelivery>\n    <ram:ApplicableHeaderTradeSettlement>\n      <ram:InvoiceCurrencyCode>EUR</ram:InvoiceCurrencyCode>\n      <ram:ApplicableTradeTax>\n        <ram:CalculatedAmount>7.91</ram:CalculatedAmount>\n        <ram:TypeCode>VAT</ram:TypeCode>\n        <ram:BasisAmount>113.03</ram:BasisAmount>\n        <ram:CategoryCode>S</ram:CategoryCode>\n        <ram:RateApplicablePercent>7.00</ram:RateApplicablePercent>\n      </ram:ApplicableTradeTax>\n      <ram:ApplicableTradeTax>\n        <ram:CalculatedAmount>12.25</ram:CalculatedAmount>\n        <ram:TypeCode>VAT</ram:TypeCode>\n        <ram:BasisAmount>64.46</ram:BasisAmount>\n        <ram:CategoryCode>S</ram:CategoryCode>\n        <ram:RateApplicablePercent>19.00</ram:RateApplicablePercent>\n      </ram:ApplicableTradeTax>\n      <ram:SpecifiedTradeAllowanceCharge>\n        <ram:ChargeIndicator>\n          <udt:Indicator>false</udt:Indicator>\n        </ram:ChargeIndicator>\n        <ram:BasisAmount>10.00</ram:BasisAmount>\n        <ram:ActualAmount>1.00</ram:ActualAmount>\n        <ram:Reason>Sondernachlass</ram:Reason>\n        <ram:CategoryTradeTax>\n          <ram:TypeCode>VAT</ram:TypeCode>\n          <ram:CategoryCode>S</ram:CategoryCode>\n          <ram:RateApplicablePercent>19.00</ram:RateApplicablePercent>\n        </ram:CategoryTradeTax>\n      </ram:SpecifiedTradeAllowanceCharge>\n      <ram:SpecifiedTradeAllowanceCharge>\n        <ram:ChargeIndicator>\n          <udt:Indicator>false</udt:Indicator>\n        </ram:ChargeIndicator>\n        <ram:BasisAmount>115.30</ram:BasisAmount>\n        <ram:ActualAmount>8.07</ram:ActualAmount>\n        <ram:Reason>Sondernachlass</ram:Reason>\n        <ram:CategoryTradeTax>\n          <ram:TypeCode>VAT</ram:TypeCode>\n          <ram:CategoryCode>S</ram:CategoryCode>\n          <ram:RateApplicablePercent>7.00</ram:RateApplicablePercent>\n        </ram:CategoryTradeTax>\n      </ram:SpecifiedTradeAllowanceCharge>\n\t    <ram:SpecifiedTradeAllowanceCharge>\n        <ram:ChargeIndicator>\n          <udt:Indicator>true</udt:Indicator>\n        </ram:ChargeIndicator>\n        <ram:BasisAmount>115.30</ram:BasisAmount>\n        <ram:ActualAmount>5.80</ram:ActualAmount>\n        <ram:Reason>Versandkosten</ram:Reason>\n        <ram:CategoryTradeTax>\n          <ram:TypeCode>VAT</ram:TypeCode>\n          <ram:CategoryCode>S</ram:CategoryCode>\n          <ram:RateApplicablePercent>7.00</ram:RateApplicablePercent>\n        </ram:CategoryTradeTax>\n      </ram:SpecifiedTradeAllowanceCharge>\n      <ram:SpecifiedTradePaymentTerms>\n        <ram:Description>Zahlbar innerhalb 30 Tagen netto bis 04.07.2018, 3% Skonto innerhalb 10 Tagen bis 15.06.2018</ram:Description>\n      </ram:SpecifiedTradePaymentTerms>\n      <ram:SpecifiedTradeSettlementHeaderMonetarySummation>\n        <ram:LineTotalAmount>180.76</ram:LineTotalAmount>\n        <ram:ChargeTotalAmount>5.80</ram:ChargeTotalAmount>\n        <ram:AllowanceTotalAmount>9.07</ram:AllowanceTotalAmount>\n        <ram:TaxBasisTotalAmount>177.49</ram:TaxBasisTotalAmount>\n\t\t<ram:TaxTotalAmount currencyID=\"EUR\">20.16</ram:TaxTotalAmount>\n        <ram:GrandTotalAmount>197.65</ram:GrandTotalAmount>\n        <ram:TotalPrepaidAmount>50.00</ram:TotalPrepaidAmount>\n        <ram:DuePayableAmount>147.65</ram:DuePayableAmount>\n      </ram:SpecifiedTradeSettlementHeaderMonetarySummation>\n    </ram:ApplicableHeaderTradeSettlement>\n  </rsm:SupplyChainTradeTransaction>\n</rsm:CrossIndustryInvoice>"
}